micropython_dps310/__init__.py
micropython_dps310/dps310.py
micropython_dps310/i2c_helpers.py
micropython_dps310-0.1.3.dist-info/LICENSE
micropython_dps310-0.1.3.dist-info/METADATA
micropython_dps310-0.1.3.dist-info/WHEEL
micropython_dps310-0.1.3.dist-info/top_level.txt
micropython_dps310-0.1.3.dist-info/RECORD
