Metadata-Version: 2.1
Name: micropython-dps310
Version: 0.1.3
Summary: MicroPython Driver for the DPS310 sensor
Author-email: "Jose D. Montoya" <dps310@mailmeto.mozmail.com>
License: MIT
Project-URL: Homepage, https://github.com/jposada202020/MicroPython_dps310
Keywords: micropython,DPS310,sensor,temperature,pressure,altitude
Classifier: Intended Audience :: Developers
Classifier: Topic :: Software Development :: Libraries
Classifier: Topic :: Software Development :: Embedded Systems
Classifier: Topic :: System :: Hardware
Classifier: License :: OSI Approved :: MIT License
Classifier: Programming Language :: Python :: Implementation :: MicroPython
License-File: LICENSE
